<?xml version="1.0" encoding="UTF-8"?>
<objects serializationModel="Studio.02.02.00">
	<object class="AudioFile" id="{014a2cb0-b74a-42e8-9aac-622cfb9fa441}">
		<property name="assetPath">
			<value>SFX/DM-CGS-08.wav</value>
		</property>
		<property name="frequencyInKHz">
			<value>44.0999985</value>
		</property>
		<property name="channelCount">
			<value>2</value>
		</property>
		<property name="length">
			<value>0.84419501133786845</value>
		</property>
		<relationship name="masterAssetFolder">
			<destination>{d65035d8-19e9-4722-bc32-47de137e629b}</destination>
		</relationship>
	</object>
</objects>
